widelearning.py
widelearning-0.8.6.dist-info/WHEEL
widelearning-0.8.6.dist-info/METADATA
widelearning-0.8.6.dist-info/RECORD
