Metadata-Version: 2.1
Name: widelearning
Version: 0.8.6
Summary: Library for searching the optimal neural network architecture
License: Apache-2.0
Author: Brinkinvision
Author-email: brinkinvision@gmail.com
Requires-Python: >=3.6,<4.0
Classifier: License :: OSI Approved :: Apache Software License
Classifier: Programming Language :: Python :: 3
Classifier: Programming Language :: Python :: 3.10
Classifier: Programming Language :: Python :: 3.6
Classifier: Programming Language :: Python :: 3.7
Classifier: Programming Language :: Python :: 3.8
Classifier: Programming Language :: Python :: 3.9
